Workbook

Sheet README
A1: Artiflex IT Cybersecurity Cluster — Updated Keyword List
A2: Source: SEO audit of 10 cybersecurity pillar pages (Apr 2026)
A3: Prepared for: Artiflex IT | mariyamjahangir@artiflexit.com
A5: How to use this workbook
A6: • Each page has its own tab (01 through 10) with the revised keyword list.
A7: • The 'New Pages Backlog' tab contains keyword clusters that support NEW pillar pages the audit recommends.
A8: • Column F (Status) shows whether a keyword is kept, revised, new, demoted, or dropped vs. the original brief.
A9: • Status colours: green = existing, amber = revised, blue = new, orange = demoted, red = dropped.
A10: • Volumes are global SERP estimates from Ahrefs/SEMrush/Keyword Planner averages — treat as directional, not precise.
A11: • Place primary/secondary keywords in H1, H2, URL, meta title, first 100 words. Long-tail in H3/body/FAQ.
A14: Legend — Keyword Type
A15: Primary | B15: Main keyword the page targets. Use in H1, meta title, URL, first paragraph.
A16: Secondary | B16: Closely related keyword. Use in H2s and multiple times in body.
A17: Long-tail | B17: Lower-volume variation or question. Use in H3, body, FAQ.
A18: Geo | B18: Geographic modifier (Dubai, UAE, GCC, Abu Dhabi). Critical for local ranking.
A19: Compliance | B19: Regulatory/standard term (NESA, SAMA, PDPL, ISO 27001, SOC 2).
A20: Comparison | B20: Head-to-head vendor comparison query (e.g., CrowdStrike vs SentinelOne).
A21: Question | B21: Natural-language question for FAQ block and People-Also-Ask capture.
A22: Partner | B22: Vendor-partnership keyword (e.g., Fortinet partner Dubai).
A23: Brand | B23: Brand or entity term — used in anchors and schema, not density.
A25: Legend — Status
A26: Existing | B26: Kept from the original brief — no change.
A27: Revised | B27: Kept but repurposed (e.g., moved from H2 to FAQ, or demoted).
A28: New | B28: Added based on audit findings — geo, compliance, comparison, question.
A29: Demoted | B29: Kept but downgraded in priority (e.g., inflated volume or wrong intent).
A30: Dropped | B30: Removed — wrong intent, cannibalisation risk, or inflated volume.
A32: Workbook summary (auto-calculated)
A33: Page | B33: Total Keywords | C33: New | D33: Revised | E33: Total Volume
A34: 01 Cybersecurity Overview | B34: =COUNT('01 Cybersecurity Overview'!C7:C200) | C34: =COUNTIF('01 Cybersecurity Overview'!F7:F200,"New") | D34: =COUNTIF('01 Cybersecurity Overview'!F7:F200,"Revised") | E34: =SUM('01 Cybersecurity Overview'!C7:C200)
A35: 02 Firewalls & Network Sec | B35: =COUNT('02 Firewalls & Network Sec'!C7:C200) | C35: =COUNTIF('02 Firewalls & Network Sec'!F7:F200,"New") | D35: =COUNTIF('02 Firewalls & Network Sec'!F7:F200,"Revised") | E35: =SUM('02 Firewalls & Network Sec'!C7:C200)
A36: 03 Endpoint Security EDR XDR | B36: =COUNT('03 Endpoint Security EDR XDR'!C7:C200) | C36: =COUNTIF('03 Endpoint Security EDR XDR'!F7:F200,"New") | D36: =COUNTIF('03 Endpoint Security EDR XDR'!F7:F200,"Revised") | E36: =SUM('03 Endpoint Security EDR XDR'!C7:C200)
A37: 04 Email Security | B37: =COUNT('04 Email Security'!C7:C200) | C37: =COUNTIF('04 Email Security'!F7:F200,"New") | D37: =COUNTIF('04 Email Security'!F7:F200,"Revised") | E37: =SUM('04 Email Security'!C7:C200)
A38: 05 Data Loss Prevention DLP | B38: =COUNT('05 Data Loss Prevention DLP'!C7:C200) | C38: =COUNTIF('05 Data Loss Prevention DLP'!F7:F200,"New") | D38: =COUNTIF('05 Data Loss Prevention DLP'!F7:F200,"Revised") | E38: =SUM('05 Data Loss Prevention DLP'!C7:C200)
A39: 06 SASE SSE CASB | B39: =COUNT('06 SASE SSE CASB'!C7:C200) | C39: =COUNTIF('06 SASE SSE CASB'!F7:F200,"New") | D39: =COUNTIF('06 SASE SSE CASB'!F7:F200,"Revised") | E39: =SUM('06 SASE SSE CASB'!C7:C200)
A40: 07 SIEM SOAR MDR | B40: =COUNT('07 SIEM SOAR MDR'!C7:C200) | C40: =COUNTIF('07 SIEM SOAR MDR'!F7:F200,"New") | D40: =COUNTIF('07 SIEM SOAR MDR'!F7:F200,"Revised") | E40: =SUM('07 SIEM SOAR MDR'!C7:C200)
A41: 08 Pen Testing & VulnMgmt | B41: =COUNT('08 Pen Testing & VulnMgmt'!C7:C200) | C41: =COUNTIF('08 Pen Testing & VulnMgmt'!F7:F200,"New") | D41: =COUNTIF('08 Pen Testing & VulnMgmt'!F7:F200,"Revised") | E41: =SUM('08 Pen Testing & VulnMgmt'!C7:C200)
A42: 09 Vendor Scorecard | B42: =COUNT('09 Vendor Scorecard'!C7:C200) | C42: =COUNTIF('09 Vendor Scorecard'!F7:F200,"New") | D42: =COUNTIF('09 Vendor Scorecard'!F7:F200,"Revised") | E42: =SUM('09 Vendor Scorecard'!C7:C200)
A43: 10 Implementation Roadmap | B43: =COUNT('10 Implementation Roadmap'!C7:C200) | C43: =COUNTIF('10 Implementation Roadmap'!F7:F200,"New") | D43: =COUNTIF('10 Implementation Roadmap'!F7:F200,"Revised") | E43: =SUM('10 Implementation Roadmap'!C7:C200)
A44: TOTAL | B44: =SUM(B34:B43) | C44: =SUM(C34:C43) | D44: =SUM(D34:D43) | E44: =SUM(E34:E43)

Sheet 01 Cybersecurity Overview
A1: 01 Cybersecurity Overview
A2: URL: https://artiflexit.com/cybersecurity-solutions
A3: Meta Title (revised): Cyber Security for Business 2026 | Artiflex IT UAE
A4: Meta Description: Protect your business with proven cybersecurity best practices — firewalls, EDR, email, DLP, SIEM. Free UAE assessment.
A6: Keyword | B6: Type | C6: Est. Monthly Volume | D6: Intent | E6: Difficulty | F6: Status | G6: Placement | H6: Notes
A7: cyber security for business | B7: Primary | C7: 3600 | D7: Commercial | E7: Hard | F7: Existing | G7: H1, Meta Title, URL, intro | H7: Anchor of the pillar; keep front-and-centre.
A8: cybersecurity solutions | B8: Secondary | C8: 6600 | D8: Commercial | E8: Hard | F8: Existing | G8: H2, body, meta description | H8: High volume — repeat 4–6x in body.
A9: cybersecurity best practices | B9: Secondary | C9: 2900 | D9: Informational | E9: Moderate | F9: Existing | G9: H2, list intro, lead magnet CTA | H9: Pairs well with the essentials checklist CTA.
A10: types of cybersecurity | B10: Long-tail | C10: 3600 | D10: Informational | E10: Moderate | F10: Existing | G10: H2 (7 pillars table) | H10: Matches the numbered solution-area table.
A11: importance of cybersecurity | B11: Long-tail | C11: 2900 | D11: Informational | E11: Moderate | F11: Existing | G11: H2 (business cost section) | H11: Natural fit for the $4.88M breach stat.
A12: cybersecurity framework | B12: Long-tail | C12: 2400 | D12: Informational | E12: Moderate | F12: Existing | G12: H2 (phased approach) | H12: Tie to NIST 5 functions.
A13: cybersecurity strategy | B13: Long-tail | C13: 2400 | D13: Commercial | E13: Moderate | F13: Existing | G13: H2, closing paragraph | H13: Also used on page 10.
A14: managed cybersecurity services | B14: Long-tail | C14: 1900 | D14: Commercial | E14: Moderate | F14: Existing | G14: H2 (why MSS makes sense) | H14: Strong conversion keyword.
A15: cybersecurity consulting services | B15: Long-tail | C15: 1300 | D15: Commercial | E15: Moderate | F15: Existing | G15: Body, CTA | H15: Good match for the 30-min free call.
A16: enterprise cybersecurity | B16: Long-tail | C16: 1300 | D16: Commercial | E16: Moderate | F16: Existing | G16: Body, comparison table
A17: cybersecurity assessment | B17: Long-tail | C17: 1000 | D17: Transactional | E17: Moderate | F17: Existing | G17: CTA, meta description | H17: Primary CTA already aligned.
A18: cybersecurity for small business | B18: Long-tail | C18: 880 | D18: Commercial | E18: Easy | F18: Existing | G18: H3, SMB paragraph
A19: cybersecurity plan | B19: Long-tail | C19: 1900 | D19: Informational | E19: Moderate | F19: Revised | G19: Internal link anchor to page 10 | H19: Avoid cannibalisation with page 10 — link out, don't compete.
A20: cybersecurity risk | B20: Long-tail | C20: 2900 | D20: Informational | E20: Moderate | F20: Existing | G20: Body
A21: what is cyber security | B21: Long-tail | C21: 9900 | D21: Informational | E21: Hard | F21: Revised | G21: FAQ block (new) | H21: Move from implicit to explicit FAQ for PAA capture.
A22: cybersecurity services UAE | B22: Geo | C22: 480 | D22: Commercial | E22: Easy | F22: New | G22: H2, meta description, LocalBusiness | H22: Highest-priority geo add — audit flagged zero geo targeting.
A23: cybersecurity company Dubai | B23: Geo | C23: 590 | D23: Commercial | E23: Moderate | F23: New | G23: H1 subtitle, footer, schema | H23: Dubai = primary commercial market.
A24: cyber security company Abu Dhabi | B24: Geo | C24: 320 | D24: Commercial | E24: Moderate | F24: New | G24: H2, city page anchor | H24: Pair with NESA compliance.
A25: cybersecurity services GCC | B25: Geo | C25: 210 | D25: Commercial | E25: Easy | F25: New | G25: Body, footer | H25: Catch Saudi/Qatar/Kuwait queries.
A26: cybersecurity services Saudi Arabia | B26: Geo | C26: 260 | D26: Commercial | E26: Moderate | F26: New | G26: Body (SAMA paragraph) | H26: Future market expansion.
A27: NESA compliance services | B27: Compliance | C27: 140 | D27: Commercial | E27: Easy | F27: New | G27: H3, meta description | H27: NESA = UAE national cyber authority.
A28: SAMA cybersecurity framework | B28: Compliance | C28: 170 | D28: Commercial | E28: Easy | F28: New | G28: H3 (compliance paragraph) | H28: Saudi Arabian Monetary Authority.
A29: UAE PDPL compliance | B29: Compliance | C29: 110 | D29: Commercial | E29: Easy | F29: New | G29: Body, schema keywords | H29: UAE data protection law.
A30: ISO 27001 consulting UAE | B30: Compliance | C30: 210 | D30: Commercial | E30: Moderate | F30: New | G30: Cross-link to compliance hub
A31: what is cybersecurity and why is it important | B31: Question | C31: 880 | D31: Informational | E31: Easy | F31: New | G31: FAQ block | H31: People-Also-Ask capture.
A32: how much do cybersecurity services cost | B32: Question | C32: 210 | D32: Commercial | E32: Easy | F32: New | G32: FAQ block | H32: Drives toward assessment CTA.
A33: how do I choose a cybersecurity provider | B33: Question | C33: 170 | D33: Commercial | E33: Easy | F33: New | G33: FAQ block | H33: Internal link to vendor scorecard.
A35: Total keywords: | B35: =COUNT(C7:C33)
A36: New keywords: | B36: =COUNTIF(F7:F33,"New")
A37: Revised keywords: | B37: =COUNTIF(F7:F33,"Revised")
A38: Total est. monthly volume: | B38: =SUM(C7:C33)

Sheet 02 Firewalls & Network Sec
A1: 02 Firewalls & Network Sec
A2: URL: https://artiflexit.com/cybersecurity/firewalls-network-security
A3: Meta Title (revised): Firewall Solutions UAE 2026 | NGFW & Managed Firewall | Artiflex IT
A4: Meta Description: Compare NGFW, UTM & managed firewalls for UAE enterprises. Fortinet, Palo Alto, Sophos. Free network assessment.
A6: Keyword | B6: Type | C6: Est. Monthly Volume | D6: Intent | E6: Difficulty | F6: Status | G6: Placement | H6: Notes
A7: network security firewall | B7: Primary | C7: 1600 | D7: Commercial | E7: Hard | F7: Existing | G7: H1, Meta Title, URL, intro
A8: network security | B8: Secondary | C8: 8100 | D8: Informational | E8: Hard | F8: Existing | G8: H2, body, meta | H8: High volume; repeat 4x.
A9: best firewall for enterprise network | B9: Secondary | C9: 880 | D9: Commercial | E9: Moderate | F9: Existing | G9: H2 (vendor comparison) | H9: Primary commercial term.
A10: next generation firewall | B10: Long-tail | C10: 2400 | D10: Informational | E10: Moderate | F10: Existing | G10: H2 (evolution section) | H10: Also NGFW acronym in parens.
A11: intrusion detection system | B11: Long-tail | C11: 2400 | D11: Informational | E11: Moderate | F11: Existing | G11: H3 (IDS/IPS paragraph)
A12: network security tools | B12: Long-tail | C12: 4400 | D12: Informational | E12: Moderate | F12: Existing | G12: Body (types section)
A13: managed firewall services | B13: Long-tail | C13: 720 | D13: Commercial | E13: Moderate | F13: Existing | G13: H2 (managed services section) | H13: Strong commercial intent.
A14: firewall security solutions | B14: Long-tail | C14: 720 | D14: Commercial | E14: Easy | F14: Existing | G14: Body
A15: network segmentation security | B15: Long-tail | C15: 590 | D15: Informational | E15: Easy | F15: Existing | G15: H2 (segmentation section)
A16: network security assessment | B16: Long-tail | C16: 590 | D16: Transactional | E16: Easy | F16: Existing | G16: Primary CTA | H16: Matches 'Request a free audit'.
A17: enterprise network security solutions | B17: Long-tail | C17: 480 | D17: Commercial | E17: Moderate | F17: Existing | G17: Body
A18: firewall vs UTM | B18: Long-tail | C18: 480 | D18: Informational | E18: Easy | F18: Existing | G18: H3, comparison callout
A19: how to secure a business network | B19: Long-tail | C19: 390 | D19: Informational | E19: Easy | F19: Existing | G19: H2 (closing paragraph)
A20: firewall installation Dubai | B20: Geo | C20: 260 | D20: Transactional | E20: Easy | F20: New | G20: Meta description, CTA block | H20: High-intent local query.
A21: firewall services UAE | B21: Geo | C21: 320 | D21: Commercial | E21: Easy | F21: New | G21: H2, body
A22: Fortinet partner UAE | B22: Partner | C22: 170 | D22: Transactional | E22: Easy | F22: New | G22: Body (vendor comparison) | H22: Confirm partner tier before publishing.
A23: Palo Alto Networks partner Dubai | B23: Partner | C23: 110 | D23: Transactional | E23: Easy | F23: New | G23: Body | H23: Validate relationship.
A24: Sophos partner UAE | B24: Partner | C24: 90 | D24: Transactional | E24: Easy | F24: New | G24: Body
A25: managed firewall services UAE | B25: Geo | C25: 140 | D25: Commercial | E25: Easy | F25: New | G25: H2, meta description | H25: High-converting long-tail.
A26: Fortinet vs Palo Alto firewall | B26: Comparison | C26: 720 | D26: Informational | E26: Moderate | F26: New | G26: H3 comparison block, FAQ | H26: Directly answers a common PAA question.
A27: Sophos vs Fortinet | B27: Comparison | C27: 390 | D27: Informational | E27: Easy | F27: New | G27: H3 comparison block
A28: Check Point vs Palo Alto | B28: Comparison | C28: 260 | D28: Informational | E28: Easy | F28: New | G28: H3 comparison block
A29: what is a next generation firewall | B29: Question | C29: 590 | D29: Informational | E29: Easy | F29: New | G29: FAQ | H29: PAA capture.
A30: how often should I update firewall rules | B30: Question | C30: 110 | D30: Informational | E30: Easy | F30: New | G30: FAQ | H30: Long-tail, low competition.
A31: firewall vs antivirus | B31: Question | C31: 880 | D31: Informational | E31: Moderate | F31: New | G31: FAQ, internal link to page 03
A33: Total keywords: | B33: =COUNT(C7:C31)
A34: New keywords: | B34: =COUNTIF(F7:F31,"New")
A35: Revised keywords: | B35: =COUNTIF(F7:F31,"Revised")
A36: Total est. monthly volume: | B36: =SUM(C7:C31)

Sheet 03 Endpoint Security EDR XDR
A1: 03 Endpoint Security EDR XDR
A2: URL: https://artiflexit.com/cybersecurity/endpoint-security-edr-xdr
A3: Meta Title (revised): Endpoint Protection UAE | EDR & XDR for Business | Artiflex IT
A4: Meta Description: Managed EDR & XDR for UAE business. Compare CrowdStrike, SentinelOne & Microsoft Defender. Free endpoint assessment.
A6: Keyword | B6: Type | C6: Est. Monthly Volume | D6: Intent | E6: Difficulty | F6: Status | G6: Placement | H6: Notes
A7: endpoint protection for business | B7: Primary | C7: 1300 | D7: Commercial | E7: Moderate | F7: Revised | G7: H1, Meta Title, URL | H7: Promoted to primary — EDR has mixed intent, this is commercial.
A8: edr cyber security | B8: Secondary | C8: 3600 | D8: Informational | E8: Moderate | F8: Revised | G8: H2, first 100 words | H8: Demoted — high informational intent, not commercial.
A9: endpoint detection and response | B9: Long-tail | C9: 75400 | D9: Informational | E9: Hard | F9: Revised | G9: H2 (explainer), FAQ | H9: Demoted — 75K volume is informational PAA; add FAQ but don't stack H1s.
A10: xdr cyber security | B10: Secondary | C10: 1260 | D10: Informational | E10: Moderate | F10: Existing | G10: H2 (XDR section)
A11: managed endpoint security | B11: Secondary | C11: 8500 | D11: Commercial | E11: Moderate | F11: Existing | G11: H2 (managed section) | H11: Strong commercial volume.
A12: ransomware protection | B12: Long-tail | C12: 11000 | D12: Commercial | E12: Hard | F12: Existing | G12: H2 (ransomware section)
A13: threat hunting | B13: Long-tail | C13: 11200 | D13: Informational | E13: Hard | F13: Revised | G13: FAQ, managed section body | H13: Demoted — broad informational; don't use in H1.
A14: what is EDR | B14: Long-tail | C14: 7690 | D14: Informational | E14: Moderate | F14: Existing | G14: FAQ block
A15: EDR vs antivirus | B15: Long-tail | C15: 820 | D15: Informational | E15: Easy | F15: Existing | G15: H3 (comparison section)
A16: next-generation antivirus | B16: Long-tail | C16: 1315 | D16: Informational | E16: Moderate | F16: Existing | G16: Body
A17: endpoint security solutions | B17: Long-tail | C17: 2900 | D17: Commercial | E17: Moderate | F17: Existing | G17: Body, vendor table
A18: advanced endpoint protection | B18: Long-tail | C18: 690 | D18: Commercial | E18: Easy | F18: Existing | G18: Body
A19: EDR solutions for small business | B19: Long-tail | C19: 320 | D19: Commercial | E19: Easy | F19: Existing | G19: H3 (SMB callout — new)
A20: endpoint security management | B20: Long-tail | C20: 760 | D20: Commercial | E20: Easy | F20: Existing | G20: Managed section
A21: managed EDR services UAE | B21: Geo | C21: 140 | D21: Commercial | E21: Easy | F21: New | G21: Meta description, CTA | H21: High-intent; low competition.
A22: endpoint security Dubai | B22: Geo | C22: 210 | D22: Commercial | E22: Easy | F22: New | G22: H2, body
A23: EDR services UAE | B23: Geo | C23: 170 | D23: Commercial | E23: Easy | F23: New | G23: Body
A24: CrowdStrike partner UAE | B24: Partner | C24: 110 | D24: Transactional | E24: Easy | F24: New | G24: Vendor comparison table | H24: Confirm partner status.
A25: SentinelOne partner Dubai | B25: Partner | C25: 90 | D25: Transactional | E25: Easy | F25: New | G25: Vendor comparison table
A26: CrowdStrike vs SentinelOne | B26: Comparison | C26: 1600 | D26: Informational | E26: Moderate | F26: New | G26: H3 comparison block, FAQ | H26: Top-3 PAA for this space.
A27: Microsoft Defender vs CrowdStrike | B27: Comparison | C27: 880 | D27: Informational | E27: Moderate | F27: New | G27: H3 comparison block
A28: Sophos Intercept X vs CrowdStrike | B28: Comparison | C28: 170 | D28: Informational | E28: Easy | F28: New | G28: Body
A29: is Microsoft Defender enough for business | B29: Question | C29: 590 | D29: Informational | E29: Easy | F29: New | G29: FAQ | H29: Very common CFO question.
A30: do I need EDR if I have antivirus | B30: Question | C30: 320 | D30: Informational | E30: Easy | F30: New | G30: FAQ
A31: EDR pricing per endpoint | B31: Question | C31: 390 | D31: Commercial | E31: Easy | F31: New | G31: FAQ (no specific prices — ranges) | H31: Careful with pricing disclosures.
A33: Total keywords: | B33: =COUNT(C7:C31)
A34: New keywords: | B34: =COUNTIF(F7:F31,"New")
A35: Revised keywords: | B35: =COUNTIF(F7:F31,"Revised")
A36: Total est. monthly volume: | B36: =SUM(C7:C31)

Sheet 04 Email Security
A1: 04 Email Security
A2: URL: https://artiflexit.com/cybersecurity/email-security
A3: Meta Title (revised): Email Security UAE | Phishing & BEC Protection | Artiflex IT
A4: Meta Description: Stop phishing & BEC attacks in UAE. AI email security, DMARC setup & Proofpoint/Mimecast. Free phishing risk test.
A6: Keyword | B6: Type | C6: Est. Monthly Volume | D6: Intent | E6: Difficulty | F6: Status | G6: Placement | H6: Notes
A7: email security solutions for business | B7: Primary | C7: 1900 | D7: Commercial | E7: Moderate | F7: Existing | G7: H1, Meta Title, URL
A8: email security | B8: Secondary | C8: 6600 | D8: Informational | E8: Hard | F8: Existing | G8: H2, body, meta
A9: phishing protection for enterprise | B9: Secondary | C9: 880 | D9: Commercial | E9: Moderate | F9: Existing | G9: H2
A10: phishing prevention solutions | B10: Long-tail | C10: 720 | D10: Commercial | E10: Easy | F10: Existing | G10: H2 (multi-layer approach)
A11: business email compromise prevention | B11: Long-tail | C11: 590 | D11: Commercial | E11: Easy | F11: Existing | G11: H2 (BEC section)
A12: AI phishing detection | B12: Long-tail | C12: 1000 | D12: Informational | E12: Easy | F12: Existing | G12: H2 (AI section)
A13: email threat protection | B13: Long-tail | C13: 480 | D13: Commercial | E13: Easy | F13: Existing | G13: Body
A14: email security gateway | B14: Long-tail | C14: 880 | D14: Informational | E14: Moderate | F14: Existing | G14: Body (Layer 1)
A15: DMARC email security | B15: Long-tail | C15: 720 | D15: Informational | E15: Easy | F15: Existing | G15: Layer 3 paragraph
A16: how to prevent phishing attacks | B16: Long-tail | C16: 1600 | D16: Informational | E16: Moderate | F16: Existing | G16: H2 (multi-layer approach)
A17: secure email for business | B17: Long-tail | C17: 480 | D17: Commercial | E17: Easy | F17: Existing | G17: Body, CTA
A18: email security best practices 2026 | B18: Long-tail | C18: 390 | D18: Informational | E18: Easy | F18: Existing | G18: H2 (best practices)
A19: phishing simulation UAE | B19: Geo | C19: 110 | D19: Transactional | E19: Easy | F19: New | G19: Primary CTA block | H19: Matches the phishing risk assessment CTA.
A20: email security services Dubai | B20: Geo | C20: 170 | D20: Commercial | E20: Easy | F20: New | G20: H2, meta description
A21: BEC protection UAE | B21: Geo | C21: 90 | D21: Commercial | E21: Easy | F21: New | G21: Body
A22: DMARC implementation Dubai | B22: Geo | C22: 70 | D22: Commercial | E22: Easy | F22: New | G22: H3 (DMARC paragraph)
A23: Proofpoint partner UAE | B23: Partner | C23: 90 | D23: Transactional | E23: Easy | F23: New | G23: Vendor table | H23: Validate.
A24: Mimecast partner UAE | B24: Partner | C24: 70 | D24: Transactional | E24: Easy | F24: New | G24: Vendor table | H24: Validate.
A25: Abnormal Security partner Middle East | B25: Partner | C25: 50 | D25: Transactional | E25: Easy | F25: New | G25: Body
A26: Proofpoint vs Mimecast | B26: Comparison | C26: 720 | D26: Informational | E26: Moderate | F26: New | G26: H3 comparison block, FAQ | H26: Top PAA question.
A27: Abnormal Security vs Proofpoint | B27: Comparison | C27: 210 | D27: Informational | E27: Easy | F27: New | G27: H3
A28: Microsoft Defender for Office vs Proofpoint | B28: Comparison | C28: 320 | D28: Informational | E28: Easy | F28: New | G28: H3
A29: what is business email compromise | B29: Question | C29: 880 | D29: Informational | E29: Moderate | F29: New | G29: FAQ
A30: how does DMARC work | B30: Question | C30: 2900 | D30: Informational | E30: Moderate | F30: New | G30: FAQ | H30: High volume, low conversion — info block only.
A31: how to stop phishing emails | B31: Question | C31: 1300 | D31: Informational | E31: Moderate | F31: New | G31: FAQ
A32: NESA email security requirements | B32: Compliance | C32: 70 | D32: Informational | E32: Easy | F32: New | G32: Body, compliance callout
A34: Total keywords: | B34: =COUNT(C7:C32)
A35: New keywords: | B35: =COUNTIF(F7:F32,"New")
A36: Revised keywords: | B36: =COUNTIF(F7:F32,"Revised")
A37: Total est. monthly volume: | B37: =SUM(C7:C32)

Sheet 05 Data Loss Prevention DLP
A1: 05 Data Loss Prevention DLP
A2: URL: https://artiflexit.com/cybersecurity/data-loss-prevention
A3: Meta Title (revised): DLP Solutions UAE | Data Loss Prevention & PDPL | Artiflex IT
A4: Meta Description: Prevent data leaks with enterprise DLP. UAE PDPL, GDPR & HIPAA compliance. Free data protection consultation.
A6: Keyword | B6: Type | C6: Est. Monthly Volume | D6: Intent | E6: Difficulty | F6: Status | G6: Placement | H6: Notes
A7: data loss prevention solutions | B7: Primary | C7: 1600 | D7: Commercial | E7: Moderate | F7: Existing | G7: H1, Meta Title, URL
A8: data security | B8: Secondary | C8: 3600 | D8: Informational | E8: Hard | F8: Existing | G8: H2, body
A9: how to prevent data leakage in a company | B9: Secondary | C9: 720 | D9: Informational | E9: Easy | F9: Existing | G9: H2 (framework section)
A10: DLP software for business | B10: Long-tail | C10: 480 | D10: Commercial | E10: Easy | F10: Existing | G10: H2 (what DLP does)
A11: enterprise data loss prevention | B11: Long-tail | C11: 590 | D11: Commercial | E11: Moderate | F11: Existing | G11: Body, vendor table
A12: data breach prevention | B12: Long-tail | C12: 880 | D12: Informational | E12: Moderate | F12: Existing | G12: Body
A13: insider threat prevention | B13: Long-tail | C13: 1050 | D13: Commercial | E13: Moderate | F13: Existing | G13: H2 (insider threat section)
A14: data classification tools | B14: Long-tail | C14: 720 | D14: Informational | E14: Easy | F14: Existing | G14: Step 1 paragraph
A15: GDPR cybersecurity compliance | B15: Compliance | C15: 2400 | D15: Commercial | E15: Moderate | F15: Existing | G15: H2 (compliance section)
A16: HIPAA data protection | B16: Compliance | C16: 590 | D16: Commercial | E16: Easy | F16: Existing | G16: Compliance section
A17: cloud DLP solutions | B17: Long-tail | C17: 390 | D17: Commercial | E17: Easy | F17: Existing | G17: Vendor table, Zscaler row
A18: data protection strategy for business | B18: Long-tail | C18: 320 | D18: Commercial | E18: Easy | F18: Existing | G18: Compliance paragraph
A19: UAE PDPL compliance | B19: Compliance | C19: 110 | D19: Commercial | E19: Easy | F19: New | G19: H2 (compliance callout) | H19: Critical — audit flagged missing UAE PDPL.
A20: PDPL data protection UAE | B20: Compliance | C20: 90 | D20: Commercial | E20: Easy | F20: New | G20: Body
A21: SAMA data protection Saudi Arabia | B21: Compliance | C21: 70 | D21: Commercial | E21: Easy | F21: New | G21: Body
A22: DLP services UAE | B22: Geo | C22: 140 | D22: Commercial | E22: Easy | F22: New | G22: Meta description, H2
A23: data loss prevention Dubai | B23: Geo | C23: 170 | D23: Commercial | E23: Easy | F23: New | G23: H2, CTA
A24: insider threat detection UAE | B24: Geo | C24: 90 | D24: Commercial | E24: Easy | F24: New | G24: Body
A25: Microsoft Purview partner UAE | B25: Partner | C25: 70 | D25: Transactional | E25: Easy | F25: New | G25: Vendor table
A26: Forcepoint partner Middle East | B26: Partner | C26: 50 | D26: Transactional | E26: Easy | F26: New | G26: Vendor table
A27: Microsoft Purview vs Symantec DLP | B27: Comparison | C27: 260 | D27: Informational | E27: Easy | F27: New | G27: H3 comparison
A28: Forcepoint vs Digital Guardian | B28: Comparison | C28: 170 | D28: Informational | E28: Easy | F28: New | G28: H3
A29: what is data loss prevention | B29: Question | C29: 1900 | D29: Informational | E29: Moderate | F29: New | G29: FAQ
A30: how to classify sensitive data | B30: Question | C30: 390 | D30: Informational | E30: Easy | F30: New | G30: FAQ, step 1 body
A31: is Microsoft 365 DLP enough | B31: Question | C31: 260 | D31: Informational | E31: Easy | F31: New | G31: FAQ
A33: Total keywords: | B33: =COUNT(C7:C31)
A34: New keywords: | B34: =COUNTIF(F7:F31,"New")
A35: Revised keywords: | B35: =COUNTIF(F7:F31,"Revised")
A36: Total est. monthly volume: | B36: =SUM(C7:C31)

Sheet 06 SASE SSE CASB
A1: 06 SASE SSE CASB
A2: URL: https://artiflexit.com/cybersecurity/workspace-protection-sse-sase
A3: Meta Title (revised): SASE & Zero Trust UAE | ZTNA, CASB, SSE | Artiflex IT
A4: Meta Description: Secure UAE remote teams with SASE, ZTNA & CASB. Replace legacy VPN. Free zero trust readiness assessment.
A6: Keyword | B6: Type | C6: Est. Monthly Volume | D6: Intent | E6: Difficulty | F6: Status | G6: Placement | H6: Notes
A7: sase cybersecurity | B7: Primary | C7: 880 | D7: Commercial | E7: Moderate | F7: Existing | G7: H1, Meta Title, URL
A8: zero trust network access for business | B8: Secondary | C8: 720 | D8: Commercial | E8: Moderate | F8: Existing | G8: H2 (ZTNA section)
A9: cloud access security broker | B9: Secondary | C9: 2400 | D9: Informational | E9: Moderate | F9: Existing | G9: H2 (CASB section)
A10: secure access service edge | B10: Long-tail | C10: 2900 | D10: Informational | E10: Moderate | F10: Existing | G10: H2 (What is SASE)
A11: zero trust security platforms | B11: Long-tail | C11: 1000 | D11: Commercial | E11: Moderate | F11: Existing | G11: H2 (implementation)
A12: SaaS security | B12: Long-tail | C12: 2900 | D12: Informational | E12: Hard | F12: Existing | G12: CASB section body
A13: remote work security solutions | B13: Long-tail | C13: 590 | D13: Commercial | E13: Easy | F13: Existing | G13: Body, opening story
A14: ZTNA vs VPN | B14: Long-tail | C14: 480 | D14: Informational | E14: Easy | F14: Existing | G14: Comparison table
A15: cloud security posture management | B15: Long-tail | C15: 690 | D15: Informational | E15: Moderate | F15: Revised | G15: Internal link to NEW CSPM pillar | H15: Audit flagged CSPM as missing pillar page; link out.
A16: secure web gateway | B16: Long-tail | C16: 1300 | D16: Informational | E16: Moderate | F16: Existing | G16: Phase 4 section
A17: hybrid cloud security | B17: Long-tail | C17: 720 | D17: Informational | E17: Moderate | F17: Existing | G17: Body
A18: workspace security for remote teams | B18: Long-tail | C18: 320 | D18: Commercial | E18: Easy | F18: Existing | G18: H2
A19: how to implement zero trust | B19: Long-tail | C19: 480 | D19: Informational | E19: Moderate | F19: Existing | G19: H2 (phased approach)
A20: SASE services UAE | B20: Geo | C20: 140 | D20: Commercial | E20: Easy | F20: New | G20: Meta description, H2
A21: zero trust UAE | B21: Geo | C21: 90 | D21: Commercial | E21: Easy | F21: New | G21: Body
A22: SASE Dubai | B22: Geo | C22: 110 | D22: Commercial | E22: Easy | F22: New | G22: H2, CTA
A23: ZTNA Dubai | B23: Geo | C23: 70 | D23: Commercial | E23: Easy | F23: New | G23: Body
A24: Zscaler partner UAE | B24: Partner | C24: 170 | D24: Transactional | E24: Easy | F24: New | G24: Vendor table | H24: Validate partner tier.
A25: Netskope partner UAE | B25: Partner | C25: 90 | D25: Transactional | E25: Easy | F25: New | G25: Vendor table
A26: Cloudflare One partner Middle East | B26: Partner | C26: 50 | D26: Transactional | E26: Easy | F26: New | G26: Vendor table
A27: Zscaler vs Netskope | B27: Comparison | C27: 480 | D27: Informational | E27: Moderate | F27: New | G27: H3 comparison block
A28: Zscaler vs Cloudflare One | B28: Comparison | C28: 210 | D28: Informational | E28: Easy | F28: New | G28: H3 comparison block
A29: Palo Alto Prisma Access vs Zscaler | B29: Comparison | C29: 390 | D29: Informational | E29: Moderate | F29: New | G29: H3 comparison block
A30: what is SASE | B30: Question | C30: 3600 | D30: Informational | E30: Hard | F30: New | G30: FAQ | H30: PAA driver — expect high impressions.
A31: is ZTNA the same as zero trust | B31: Question | C31: 260 | D31: Informational | E31: Easy | F31: New | G31: FAQ
A32: SASE vs SSE | B32: Comparison | C32: 390 | D32: Informational | E32: Easy | F32: New | G32: H3 or FAQ
A34: Total keywords: | B34: =COUNT(C7:C32)
A35: New keywords: | B35: =COUNTIF(F7:F32,"New")
A36: Revised keywords: | B36: =COUNTIF(F7:F32,"Revised")
A37: Total est. monthly volume: | B37: =SUM(C7:C32)

Sheet 07 SIEM SOAR MDR
A1: 07 SIEM SOAR MDR
A2: URL: https://artiflexit.com/cybersecurity/siem-soar-mdr
A3: Meta Title (revised): SIEM & MDR UAE | 24/7 Security Monitoring | Artiflex IT
A4: Meta Description: SIEM, SOAR & MDR for UAE businesses. 24/7 SOC-as-a-Service with Splunk, Sentinel & CrowdStrike. Free assessment.
A6: Keyword | B6: Type | C6: Est. Monthly Volume | D6: Intent | E6: Difficulty | F6: Status | G6: Placement | H6: Notes
A7: siem cyber security | B7: Primary | C7: 4400 | D7: Commercial | E7: Moderate | F7: Existing | G7: H1, Meta Title, URL
A8: mdr cybersecurity | B8: Secondary | C8: 1600 | D8: Commercial | E8: Moderate | F8: Existing | G8: H2 (MDR section)
A9: SIEM solutions | B9: Secondary | C9: 5400 | D9: Commercial | E9: Hard | F9: Existing | G9: H2, body
A10: security orchestration tools | B10: Long-tail | C10: 1300 | D10: Informational | E10: Moderate | F10: Existing | G10: H2 (SOAR section)
A11: managed detection and response | B11: Long-tail | C11: 1100 | D11: Commercial | E11: Moderate | F11: Existing | G11: H2 (MDR section)
A12: cybersecurity monitoring software | B12: Long-tail | C12: 1900 | D12: Commercial | E12: Moderate | F12: Existing | G12: Body
A13: threat detection tools | B13: Long-tail | C13: 3600 | D13: Informational | E13: Moderate | F13: Existing | G13: H2 (threat detection section)
A14: SIEM vs SOAR vs MDR | B14: Long-tail | C14: 590 | D14: Informational | E14: Easy | F14: Existing | G14: H2 (comparison)
A15: best SIEM tools for business | B15: Long-tail | C15: 480 | D15: Commercial | E15: Easy | F15: Existing | G15: Vendor comparison table
A16: SOC as a service | B16: Long-tail | C16: 880 | D16: Commercial | E16: Moderate | F16: Existing | G16: MDR section
A17: cybersecurity automation tools | B17: Long-tail | C17: 880 | D17: Informational | E17: Moderate | F17: Existing | G17: SOAR section
A18: 24/7 security monitoring | B18: Long-tail | C18: 590 | D18: Commercial | E18: Easy | F18: Existing | G18: Meta description, MDR body
... A27: Arctic Wolf MDR Middle East | B27: Partner | C27: 40 | D27: Transactional | E27: Easy | F27: New | G27: Vendor table
A28: Splunk vs Microsoft Sentinel | B28: Comparison | C28: 720 | D28: Informational | E28: Moderate | F28: New | G28: H3 comparison block | H28: Top PAA.
A29: Microsoft Sentinel vs QRadar | B29: Comparison | C29: 260 | D29: Informational | E29: Easy | F29: New | G29: H3
A30: CrowdStrike Falcon Complete vs Arctic Wolf | B30: Comparison | C30: 210 | D30: Informational | E30: Easy | F30: New | G30: H3
A31: what is the difference between SIEM and SOAR | B31: Question | C31: 390 | D31: Informational | E31: Easy | F31: New | G31: FAQ
A32: do I need SIEM or MDR | B32: Question | C32: 320 | D32: Informational | E32: Easy | F32: New | G32: FAQ
A33: how much does MDR cost | B33: Question | C33: 260 | D33: Commercial | E33: Easy | F33: New | G33: FAQ (ranges only)
A34: NESA SOC requirements UAE | B34: Compliance | C34: 40 | D34: Commercial | E34: Easy | F34: New | G34: Body, compliance callout
A36: Total keywords: | B36: =COUNT(C7:C34)
A37: New keywords: | B37: =COUNTIF(F7:F34,"New")
A38: Revised keywords: | B38: =COUNTIF(F7:F34,"Revised")
A39: Total est. monthly volume: | B39: =SUM(C7:C34)

Sheet 08 Pen Testing & VulnMgmt
A1: 08 Pen Testing & VulnMgmt
A2: URL: https://artiflexit.com/cybersecurity/vulnerability-management
A3: Meta Title (revised): Penetration Testing UAE | VAPT Services | Artiflex IT 2026
A4: Meta Description: CREST-aligned pen testing in UAE — web, network, API, cloud & red team. VAPT for NESA, SAMA, ISO 27001, PCI.
A6: Keyword | B6: Type | C6: Est. Monthly Volume | D6: Intent | E6: Difficulty | F6: Status | G6: Placement | H6: Notes
A7: penetration testing services | B7: Primary | C7: 9000 | D7: Commercial | E7: Hard | F7: Existing | G7: H1, Meta Title, URL
A8: vulnerability management for business | B8: Secondary | C8: 1300 | D8: Commercial | E8: Moderate | F8: Existing | G8: H2, body
A9: vulnerability assessment | B9: Secondary | C9: 11000 | D9: Commercial | E9: Hard | F9: Existing | G9: H2 (assessment vs pen test)
A10: security audit | B10: Long-tail | C10: 14000 | D10: Commercial | E10: Hard | F10: Existing | G10: H2 (security audit section)
A11: web application penetration testing | B11: Long-tail | C11: 15000 | D11: Commercial | E11: Hard | F11: Existing | G11: H3 (types of pen testing)
A12: network penetration testing | B12: Long-tail | C12: 1700 | D12: Commercial | E12: Moderate | F12: Existing | G12: H3
A13: API penetration testing | B13: Long-tail | C13: 1290 | D13: Commercial | E13: Moderate | F13: Existing | G13: H3
A14: external penetration testing | B14: Long-tail | C14: 980 | D14: Commercial | E14: Easy | F14: Existing | G14: Body
A15: cloud penetration testing | B15: Long-tail | C15: 870 | D15: Commercial | E15: Moderate | F15: Existing | G15: H3
A16: ethical hacking services | B16: Long-tail | C16: 1300 | D16: Commercial | E16: Moderate | F16: Existing | G16: Body
A17: vulnerability scanning tools | B17: Long-tail | C17: 3200 | D17: Informational | E17: Moderate | F17: Existing | G17: H2 (assessment vs pen test)
A18: red teaming | B18: Long-tail | C18: 1800 | D18: Informational | E18: Hard | F18: Revised | G18: H3 (red team section) | H18: DEMOTED — original '93,200/mo' was dataset noise; realistic volume ≈1.8K. Don't treat as primary.
A19: penetration testing report template | B19: Long-tail | C19: 900 | D19: Informational | E19: Easy | F19: Existing | G19: H2 (what a good report looks like)
A20: penetration testing services UAE | B20: Geo | C20: 390 | D20: Transactional | E20: Moderate | F20: New | G20: Meta description, H1 subtitle, CTA | H20: HIGHEST-priority geo add for this page.
A21: penetration testing Dubai | B21: Geo | C21: 480 | D21: Transactional | E21: Moderate | F21: New | G21: H2, body
A22: penetration testing Abu Dhabi | B22: Geo | C22: 170 | D22: Transactional | E22: Easy | F22: New | G22: Body, city page
A23: VAPT services UAE | B23: Geo | C23: 260 | D23: Transactional | E23: Easy | F23: New | G23: H2 | H23: Vulnerability Assessment & Penetration Testing — UAE-popular acronym.
A24: CREST penetration testing UAE | B24: Compliance | C24: 90 | D24: Commercial | E24: Easy | F24: New | G24: Body, trust signals | H24: Confirm CREST accreditation before claiming.
A25: OSCP certified pen testers | B25: Compliance | C25: 140 | D25: Commercial | E25: Easy | F25: New | G25: Team credentials sidebar
A26: NESA penetration testing requirements | B26: Compliance | C26: 40 | D26: Commercial | E26: Easy | F26: New | G26: Compliance callout
A27: SAMA penetration testing Saudi Arabia | B27: Compliance | C27: 30 | D27: Commercial | E27: Easy | F27: New | G27: Compliance callout
A28: PCI DSS penetration testing UAE | B28: Compliance | C28: 70 | D28: Commercial | E28: Easy | F28: New | G28: Body
A29: ISO 27001 penetration testing | B29: Compliance | C29: 210 | D29: Commercial | E29: Moderate | F29: New | G29: Body
A30: pen test vs vulnerability scan | B30: Question | C30: 590 | D30: Informational | E30: Easy | F30: New | G30: FAQ
A31: how often should you do a penetration test | B31: Question | C31: 260 | D31: Informational | E31: Easy | F31: New | G31: FAQ
A32: how much does a penetration test cost | B32: Question | C32: 720 | D32: Commercial | E32: Moderate | F32: New | G32: FAQ (ranges only)
A33: what is VAPT | B33: Question | C33: 880 | D33: Informational | E33: Easy | F33: New | G33: FAQ | H33: Very common UAE search query.
A34: black box vs white box penetration testing | B34: Question | C34: 260 | D34: Informational | E34: Easy | F34: New | G34: FAQ
A36: Total keywords: | B36: =COUNT(C7:C34)
A37: New keywords: | B37: =COUNTIF(F7:F34,"New")
A38: Revised keywords: | B38: =COUNTIF(F7:F34,"Revised")
A39: Total est. monthly volume: | B39: =SUM(C7:C34)

Sheet 09 Vendor Scorecard
A1: 09 Vendor Scorecard
A2: URL: https://artiflexit.com/cybersecurity/vendor-scorecard
A3: Meta Title (revised): Best Cybersecurity Vendors 2026 UAE | Artiflex IT Scorecard
A4: Meta Description: Vendor-neutral 2026 cybersecurity scorecard. EDR, SIEM, SASE & firewall rankings for UAE buyers. Free shortlist.
A6: Keyword | B6: Type | C6: Est. Monthly Volume | D6: Intent | E6: Difficulty | F6: Status | G6: Placement | H6: Notes
A7: best cybersecurity vendors 2026 | B7: Primary | C7: 1900 | D7: Commercial | E7: Moderate | F7: Existing | G7: H1, Meta Title, URL
A8: cybersecurity vendor comparison | B8: Secondary | C8: 1300 | D8: Commercial | E8: Moderate | F8: Existing | G8: H2, body
A9: best cybersecurity tools | B9: Secondary | C9: 9900 | D9: Commercial | E9: Hard | F9: Existing | G9: H2 (best tools by category)
A10: top cybersecurity companies | B10: Long-tail | C10: 1600 | D10: Informational | E10: Moderate | F10: Existing | G10: H2, intro
A11: cybersecurity software | B11: Long-tail | C11: 6600 | D11: Informational | E11: Hard | F11: Existing | G11: Body, meta
A12: managed security service providers | B12: Long-tail | C12: 1900 | D12: Commercial | E12: Moderate | F12: Existing | G12: H2 (MSSP vs MDR)
A13: how to evaluate cybersecurity vendors | B13: Long-tail | C13: 320 | D13: Informational | E13: Easy | F13: Existing | G13: H2 (practical tips)
A14: cybersecurity vendor risk assessment | B14: Long-tail | C14: 590 | D14: Informational | E14: Easy | F14: Existing | G14: Body
A15: EDR vs XDR pros and cons | B15: Long-tail | C15: 600 | D15: Informational | E15: Easy | F15: Existing | G15: H3 (endpoint section)
A16: best SIEM tools 2026 | B16: Long-tail | C16: 480 | D16: Commercial | E16: Easy | F16: Existing | G16: H3 (SIEM section)
A17: cybersecurity vendor selection criteria | B17: Long-tail | C17: 260 | D17: Informational | E17: Easy | F17: Existing | G17: H2 (scoring methodology)
A18: cybersecurity product reviews | B18: Long-tail | C18: 390 | D18: Informational | E18: Easy | F18: Revised | G18: Body — drop 'pay-to-play' claim | H18: LEGAL: rewrite — audit flagged defamation risk.
A19: cybersecurity vendor comparison UAE | B19: Geo | C19: 90 | D19: Commercial | E19: Easy | F19: New | G19: Meta description, H2
A20: MSSP UAE | B20: Geo | C20: 170 | D20: Commercial | E20: Easy | F20: New | G20: Body, MSSP section
A21: best cybersecurity company Dubai | B21: Geo | C21: 140 | D21: Commercial | E21: Easy | F21: New | G21: H2, body
A22: cybersecurity partner UAE | B22: Partner | C22: 90 | D22: Commercial | E22: Easy | F22: New | G22: Body
A23: CrowdStrike vs SentinelOne 2026 | B23: Comparison | C23: 880 | D23: Informational | E23: Moderate | F23: New | G23: H3 under endpoint
A24: Splunk vs Microsoft Sentinel 2026 | B24: Comparison | C24: 480 | D24: Informational | E24: Moderate | F24: New | G24: H3 under SIEM
A25: Zscaler vs Palo Alto Prisma Access | B25: Comparison | C25: 320 | D25: Informational | E25: Easy | F25: New | G25: H3 under SASE
A26: Fortinet vs Palo Alto 2026 | B26: Comparison | C26: 590 | D26: Informational | E26: Moderate | F26: New | G26: Add firewall comparison H2 | H26: Audit flagged missing firewall category.
A27: Proofpoint vs Abnormal Security | B27: Comparison | C27: 210 | D27: Informational | E27: Easy | F27: New | G27: Add email security H2 | H27: Audit flagged missing email security category.
A28: how do I choose a cybersecurity vendor | B28: Question | C28: 320 | D28: Informational | E28: Easy | F28: New | G28: FAQ
A29: what is the best EDR solution | B29: Question | C29: 390 | D29: Informational | E29: Easy | F29: New | G29: FAQ
A30: what is the best SIEM | B30: Question | C30: 260 | D30: Informational | E30: Easy | F30: New | G30: FAQ
A31: is Microsoft Defender enough | B31: Question | C31: 590 | D31: Informational | E31: Easy | F31: New | G31: FAQ
A32: MSSP vs MDR | B32: Comparison | C32: 320 | D32: Informational | E32: Easy | F32: New | G32: H3 (existing section — expand)
A34: Total keywords: | B34: =COUNT(C7:C32)
A35: New keywords: | B35: =COUNTIF(F7:F32,"New")
A36: Revised keywords: | B36: =COUNTIF(F7:F32,"Revised")
A37: Total est. monthly volume: | B37: =SUM(C7:C32)

Sheet 10 Implementation Roadmap
A1: 10 Implementation Roadmap
A2: URL: https://artiflexit.com/cybersecurity/implementation-roadmap
A3: Meta Title (revised): Cybersecurity Strategy UAE | NIST Roadmap | Artiflex IT
A4: Meta Description: Build your UAE cybersecurity strategy with NIST CSF 2.0. 30-60-90 roadmap, NESA/SAMA alignment. Free workshop.
A6: Keyword | B6: Type | C6: Est. Monthly Volume | D6: Intent | E6: Difficulty | F6: Status | G6: Placement | H6: Notes
A7: cyber security strategy for business | B7: Primary | C7: 2900 | D7: Commercial | E7: Moderate | F7: Existing | G7: H1, Meta Title, URL
A8: cybersecurity implementation roadmap | B8: Secondary | C8: 720 | D8: Commercial | E8: Moderate | F8: Existing | G8: H2, body
A9: cybersecurity plan | B9: Secondary | C9: 1900 | D9: Informational | E9: Moderate | F9: Existing | G9: H2 (30-60-90 plan)
A10: cybersecurity policy | B10: Long-tail | C10: 2400 | D10: Informational | E10: Moderate | F10: Existing | G10: Body, day 31–60 section
A11: cybersecurity framework | B11: Long-tail | C11: 2400 | D11: Informational | E11: Moderate | F11: Existing | G11: H2 (NIST foundation)
A12: how to build a cybersecurity program | B12: Long-tail | C12: 480 | D12: Informational | E12: Easy | F12: Existing | G12: Intro, maturity model
A13: cybersecurity budget planning | B13: Long-tail | C13: 390 | D13: Informational | E13: Easy | F13: Existing | G13: H2 (budget section)
A14: cybersecurity maturity model | B14: Long-tail | C14: 590 | D14: Informational | E14: Easy | F14: Existing | G14: H2 (maturity model section)
A15: NIST cybersecurity framework implementation | B15: Long-tail | C15: 720 | D15: Informational | E15: Moderate | F15: Existing | G15: H2 (NIST foundation)
A16: cybersecurity ROI for business | B16: Long-tail | C16: 320 | D16: Informational | E16: Easy | F16: Existing | G16: H2 (ROI section)
A17: cybersecurity risk assessment | B17: Long-tail | C17: 1600 | D17: Commercial | E17: Moderate | F17: Existing | G17: Day 1–30, primary CTA
A18: 30 60 90 day cybersecurity plan | B18: Long-tail | C18: 260 | D18: Informational | E18: Easy | F18: Existing | G18: H2 (30-60-90 plan)
... A23: ISO 27001 implementation UAE | B23: Compliance | C23: 260 | D23: Commercial | E23: Moderate | F23: New | G23: Body
A24: NIST CSF 2.0 implementation | B24: Compliance | C24: 590 | D24: Informational | E24: Moderate | F24: New | G24: Update NIST section to CSF 2.0 | H24: Audit flagged — NIST CSF 2.0 released 2024.
A25: SOC 2 readiness UAE | B25: Compliance | C25: 110 | D25: Commercial | E25: Easy | F25: New | G25: Body
A26: cybersecurity strategy workshop | B26: Long-tail | C26: 90 | D26: Transactional | E26: Easy | F26: New | G26: Primary CTA | H26: Matches the 90-minute workshop callout.
A27: virtual CISO services UAE | B27: Geo | C27: 170 | D27: Commercial | E27: Easy | F27: New | G27: Body — new pillar stub
A28: how much should a company spend on cybersecurity | B28: Question | C28: 390 | D28: Informational | E28: Easy | F28: New | G28: FAQ
A29: what is the NIST cybersecurity framework | B29: Question | C29: 1900 | D29: Informational | E29: Moderate | F29: New | G29: FAQ
A30: how do you measure cybersecurity maturity | B30: Question | C30: 170 | D30: Informational | E30: Easy | F30: New | G30: FAQ, maturity section
A31: what is cybersecurity ROI | B31: Question | C31: 140 | D31: Informational | E31: Easy | F31: New | G31: FAQ
A33: Total keywords: | B33: =COUNT(C7:C31)
A34: New keywords: | B34: =COUNTIF(F7:F31,"New")
A35: Revised keywords: | B35: =COUNTIF(F7:F31,"Revised")
A36: Total est. monthly volume: | B36: =SUM(C7:C31)

Sheet New Pages Backlog
A1: Recommended NEW Pillar Pages (from audit)
A2: Build these pages to close topical gaps the existing 10-page cluster leaves. Ranked by priority.
A4: Proposed Page | B4: URL Slug | C4: Primary Keyword | D4: Est. Volume | E4: Intent | F4: Priority | G4: Why it matters
A5: Identity & Access Management (IAM) | B5: /cybersecurity/identity-access-management | C5: identity and access management | D5: 14800 | E5: Commercial | F5: High | G5: Orphaned pillar — all SASE/ZTNA pages reference IAM but there's no hub page. MFA, SSO, PAM, IGA all sit here.
A6: Privileged Access Management (PAM) | B6: /cybersecurity/privileged-access-management | C6: privileged access management | D6: 4400 | E6: Commercial | F6: High | G6: CyberArk/BeyondTrust/Delinea — high commercial intent, regulated industries mandatory.
A7: Backup, DR & Ransomware Recovery | B7: /cybersecurity/backup-disaster-recovery | C7: ransomware backup and recovery | D7: 2400 | E7: Commercial | F7: High | G7: Page 03 & 10 reference BCDR but no hub. Veeam/Rubrik/Cohesity partners.
A8: Cloud Security Posture Management (CSPM) | B8: /cybersecurity/cloud-security-posture | C8: cloud security posture management | D8: 690 | E8: Commercial | F8: High | G8: Page 06 already links to a non-existent CSPM page. Wiz/Prisma Cloud/Orca.
A9: Security Awareness Training (SAT) | B9: /cybersecurity/security-awareness-training | C9: security awareness training | D9: 9900 | E9: Commercial | F9: High | G9: Page 04 mentions but no pillar. KnowBe4/Proofpoint/Cofense.
A10: Compliance Hub (NESA, SAMA, PDPL, ISO 27001) | B10: /cybersecurity/compliance-uae | C10: NESA compliance UAE | D10: 390 | E10: Commercial | F10: Critical | G10: Audit priority #1 — collects all UAE/GCC compliance keywords and interlinks the cluster.
A11: OT / ICS Security | B11: /cybersecurity/ot-ics-security | C11: OT cybersecurity | D11: 1300 | E11: Commercial | F11: Medium | G11: Critical for UAE oil & gas / utilities. Claroty, Nozomi, Dragos.
A12: Mobile Device Security / MDM | B12: /cybersecurity/mobile-device-management | C12: mobile device management | D12: 8100 | E12: Commercial | F12: Medium | G12: Intune/Jamf/Workspace ONE. Cross-link from page 03.
A13: Dark Web Monitoring & Threat Intel | B13: /cybersecurity/threat-intelligence | C13: dark web monitoring services | D13: 1600 | E13: Commercial | F13: Medium | G13: Recorded Future, Flashpoint, Intel 471. Cross-link from pages 07, 08.
A14: Incident Response Retainer | B14: /cybersecurity/incident-response | C14: incident response services | D14: 720 | E14: Transactional | F14: Medium | G14: Page 07 references but no dedicated page. Mandiant/Unit 42/CrowdStrike Services.
A15: Virtual CISO (vCISO) | B15: /cybersecurity/virtual-ciso-uae | C15: virtual CISO services | D15: 1900 | E15: Commercial | F15: High | G15: High-margin consulting offer. Natural fit with page 10 roadmap.
A16: Ransomware Protection Hub | B16: /cybersecurity/ransomware-protection | C16: ransomware protection | D16: 11000 | E16: Commercial | F16: Medium | G16: Consolidates endpoint, email, backup angles. Redirect target for ransomware queries.
... A18: IoT Security | B18: /cybersecurity/iot-security | C18: IoT security solutions | D18: 1900 | E18: Commercial | F18: Low | G18: Emerging — OT-adjacent, tie to smart-city initiatives.
A20: Total backlog pages: | B20: =COUNTA(A5:A18)
A21: Combined monthly volume: | B21: =SUM(D5:D18)
